{
  "button_hints": "অ্যাপ সম্পর্কে আপনার মতামত জানিয়ে আমাদের অনুপ্রাণিত করতে 5 star রেটিং দিন ও অ্যাপের কার্যক্রম চালিয়ে নিতে আর্থিক সহযোগিতা করুন",
  "button_text": "৫ স্টার রেটিং দিন",
  "button_url": "https://play.google.com/store/apps/details?id=theoaktroop.appoframadan",
  "content_message": "ঘুমাতে যাওয়ার আগে রাসূল (সা) বেশ কিছু আমল করতেন। এই সুন্নাহগুলো পালন করার মাধ্যমে আমরা আমাদের ঘুমকেও ইবাদতের সমতুল্য করে তুলতে পারি। \nঘুমানোর আগের সুন্নাহগুলো নিচে পয়েন্ট আকারে সংক্ষিপ্ত ভাবে তুলে ধরা হলোঃ\n\n১. ব্যবহার্য থালা-বাসন, হাড়ি-পাতিল ঢেকে রাখা ও বাতি নিভিয়ে দেয়া\n২. অযু করা\n৩. ঘুমের পূর্বে পড়ার জন্য বিশেষ কয়েকটি দুয়া আছে সেগুলো পড়া\n৪. সূরা কাফিরুন, সূরা ইখলাস, সূরা ফালাক্ব ও সূরা নাস পড়া\n৫. ৩৩ বার সুবহানাল্লাহ, ৩৩ বার আলহামদুলিল্লাহ ও ৩৪ বার আল্লাহু আকবার পড়া\n৬. আয়াতুল কুরসী পড়া\n৭. সূরা বাক্বারার শেষ দুই আয়াত পড়া\n৮. সূরা সাজদাহ ও সূরা মুলক পড়া\n৯. ডান কাত হয়ে ঘুমানো\n\nঘুমার পূর্বে পড়ার মত অনেকগুলো দুআ রয়েছে। তার মধ্যে নিচের দুআটি সবচেয়ে সহজঃ\n\nبِاسْمِكَ اللّٰهُمَّ أَمُوْتُ وَأَحْيَا\n\nহে আল্লাহ ! আপনার নাম নিয়েই আমি মরছি (ঘুমাচ্ছি) এবং আপনার নাম নিয়েই জীবিত (জাগ্রত) হবো।\n(বুখারী ৬৩২৪ - আরবি ইবারত সহ মূল হাদীসটি পাওয়া যাবে এখানেঃ http://ihadis.com/books/bukhari/hadis/6324)\n\nউপরের পয়েন্টগুলোর বিস্তারিত বিবরণ এবং হাদীসের দলিল সহ ঘুমানোর পূর্বে পাঠ করার মত মোট ৬ট দুআ পড়ার জন্য ভিজিট করুন এই লিংকেঃ\nhttps://hellohasan.com/2021/06/15/ঘুমানোর-পূর্বের-আমল\n\nএছাড়াও আমাদের অ্যাপের দুআ সেকশনের \"দৈনন্দিন জীবন\" অধ্যায়ের শুরুতেই বিস্তারিত লেখাটি পাওয়া যাবে।\nআল্লাহ আমাদের সকলের ঘুমকে নবীজির (সা) দেখানো পদ্ধতি অনুসরণের মাধ্যমে, ইবাদতে পরিণত করার তাওফিক দান করুন। আমীন।",
  "content_title": "ঘুমানোর পূর্বের সুন্নাহ নির্দেশিত আমল সমূহ"
}
